{
  "id": "Han_Empire_-100",
  "name": "漢",
  "year": -100,
  "facts": [
    "首都: 長安",
    "皇帝: 武帝（在位前141-87年）",
    "政体: 帝政",
    "領土: 朝鮮、西域まで拡大",
    "特徴: 漢の最盛期、シルクロード開通"
  ],
  "keyEvents": [
    {
      "year": -206,
      "event": "秦滅亡、楚漢戦争開始"
    },
    {
      "year": -202,
      "event": "劉邦が漢を建国（高祖）"
    },
    {
      "year": -200,
      "event": "白登山の戦い（匈奴に敗北）"
    },
    {
      "year": -141,
      "event": "武帝即位"
    },
    {
      "year": -139,
      "event": "張騫を西域に派遣（シルクロード開通）"
    },
    {
      "year": -119,
      "event": "匈奴を撃破（衛青・霍去病）"
    },
    {
      "year": 8,
      "event": "王莽による簒奪（新の建国）"
    },
    {
      "year": 25,
      "event": "光武帝が後漢を再興"
    },
    {
      "year": 184,
      "event": "黄巾の乱"
    },
    {
      "year": 220,
      "event": "後漢滅亡"
    }
  ],
  "aiGenerated": true
}
